mcp_scan/MCPScanner.py
mcp_scan/Storage.py
mcp_scan/__init__.py
mcp_scan/cli.py
mcp_scan/direct_scanner.py
mcp_scan/gateway.py
mcp_scan/identity.py
mcp_scan/lib.py
mcp_scan/mcp_client.py
mcp_scan/mcp_server.py
mcp_scan/models.py
mcp_scan/policy.gr
mcp_scan/printer.py
mcp_scan/redact.py
mcp_scan/run.py
mcp_scan/signed_binary.py
mcp_scan/traffic_capture.py
mcp_scan/upload.py
mcp_scan/utils.py
mcp_scan/verify_api.py
mcp_scan/version.py
mcp_scan/well_known_clients.py
mcp_scan_server/__init__.py
mcp_scan_server/activity_logger.py
mcp_scan_server/format_guardrail.py
mcp_scan_server/models.py
mcp_scan_server/parse_config.py
mcp_scan_server/server.py
mcp_scan_server/session_store.py
mcp_scan_server/guardrail_templates/__init__.py
mcp_scan_server/guardrail_templates/links.gr
mcp_scan_server/guardrail_templates/moderated.gr
mcp_scan_server/guardrail_templates/pii.gr
mcp_scan_server/guardrail_templates/secrets.gr
mcp_scan_server/guardrail_templates/tool_templates/disable_tool.gr
mcp_scan_server/routes/__init__.py
mcp_scan_server/routes/policies.py
mcp_scan_server/routes/push.py
mcp_scan_server/routes/trace.py
mcp_scan_server/routes/user.py
mcp_scan-0.3.36.dist-info/METADATA
mcp_scan-0.3.36.dist-info/WHEEL
mcp_scan-0.3.36.dist-info/entry_points.txt
mcp_scan-0.3.36.dist-info/licenses/LICENSE
mcp_scan-0.3.36.dist-info/RECORD
