Metadata-Version: 2.4
Name: mcp-scan
Version: 0.3.36
Summary: MCP Scan tool
License: Apache-2.0
License-File: LICENSE
Classifier: Operating System :: OS Independent
Classifier: Programming Language :: Python :: 3
Requires-Python: >=3.10
Requires-Dist: aiofiles>=23.1.0
Requires-Dist: aiohttp>=3.11.16
Requires-Dist: fastapi>=0.115.12
Requires-Dist: filelock>=3.18.0
Requires-Dist: lark>=1.1.9
Requires-Dist: mcp[cli]==1.16.0
Requires-Dist: psutil>=5.9.0
Requires-Dist: pydantic-core>=2.41.4
Requires-Dist: pydantic>=2.11.2
Requires-Dist: pyjson5>=1.6.8
Requires-Dist: pyyaml>=6.0.2
Requires-Dist: rapidfuzz>=3.13.0
Requires-Dist: regex>=2024.11.6
Requires-Dist: rich>=14.0.0
Requires-Dist: truststore>=0.10.4
Requires-Dist: types-aiofiles
Requires-Dist: uvicorn>=0.34.2
Provides-Extra: dev
Requires-Dist: pyinstaller>=6.15.0; extra == 'dev'
Requires-Dist: ruff>=0.11.8; extra == 'dev'
Requires-Dist: shiv>=1.0.4; extra == 'dev'
Provides-Extra: proxy
Requires-Dist: invariant-ai>=0.3.3; extra == 'proxy'
Requires-Dist: invariant-sdk>=0.0.11; extra == 'proxy'
Provides-Extra: test
Requires-Dist: pytest-asyncio>=0.26.0; extra == 'test'
Requires-Dist: pytest-lazy-fixtures>=1.1.2; extra == 'test'
Requires-Dist: pytest>=7.4.0; extra == 'test'
